marishque_mouse/__init__.py
marishque_mouse/_modidx.py
marishque_mouse/core.py
marishque_mouse/mouse.py
marishque_mouse-0.0.2.dist-info/LICENSE
marishque_mouse-0.0.2.dist-info/METADATA
marishque_mouse-0.0.2.dist-info/WHEEL
marishque_mouse-0.0.2.dist-info/entry_points.txt
marishque_mouse-0.0.2.dist-info/top_level.txt
marishque_mouse-0.0.2.dist-info/RECORD
